<Database>
  <GameDBStringTable ID="LOC_TR_ADDON_CRP_SYMPTOMS">
    <LanguageCode>tr</LanguageCode>
    <LanguageNameLocalized>Türkçe</LanguageNameLocalized>
    <Contributors>
      <Name>gokustan</Name>
    </Contributors>
    <LocalizedStrings>
      
    
	<!-- ### ### -->
	<!-- ######################################## Content From OBGYN ######################################## -->
	<!-- ### ### -->
	
	
    <GameDBLocalizedString>
        <LocID>SYM_CRP_RH-</LocID>
        <Text>Anti-eritrosit alloimmünizasyon</Text>
      </GameDBLocalizedString>
      <GameDBLocalizedString>
        <LocID>SYM_CRP_RH-_DESCRIPTION</LocID>
        <Text>Alloimmünizasyon, genetik olarak farklı hücre veya dokulara maruziyet sonucu gelişen, antijenlere karşı immün yanıtı ifade eder.</Text>
      </GameDBLocalizedString>
      <GameDBLocalizedString>
        <LocID>SYM_CRP_METRORRAGIE</LocID>
        <Text>Metroraji</Text>
      </GameDBLocalizedString>
      <GameDBLocalizedString>
        <LocID>SYM_CRP_METRORRAGIE_DESCRIPTION</LocID>
        <Text>Olağan adet günleri dışında kanama gerçekleşmesidir.</Text>
      </GameDBLocalizedString>
      <GameDBLocalizedString>
        <LocID>SYM_CRP_RETARD_REGLE</LocID>
        <Text>Adet gecikmesi</Text>
      </GameDBLocalizedString>
      <GameDBLocalizedString>
        <LocID>SYM_CRP_RETARD_REGLE_DESCRIPTION</LocID>
        <Text>Hastanın adeti gecikmiş.</Text>
      </GameDBLocalizedString>
      <GameDBLocalizedString>
        <LocID>SYM_CRP_GROSSESSE</LocID>
        <Text>Gebelik</Text>
      </GameDBLocalizedString>
      <GameDBLocalizedString>
        <LocID>SYM_CRP_GROSSESSE_DESCRIPTION</LocID>
        <Text>Gebe olma halidir.</Text>
      </GameDBLocalizedString>
      <GameDBLocalizedString>
        <LocID>SYM_CRP_HEMOPERITOINE</LocID>
        <Text>Hemoperitoneum</Text>
      </GameDBLocalizedString>
      <GameDBLocalizedString>
        <LocID>SYM_CRP_HEMOPERITOINE_DESCRIPTION</LocID>
        <Text>Hemoperitoneum, peritoneal kavitede kan bulunması durumudur.</Text>
      </GameDBLocalizedString>
      <GameDBLocalizedString>
        <LocID>SYM_CRP_HYPERANDROGEN</LocID>
        <Text>Biyolojik hiperandrojenizm</Text>
      </GameDBLocalizedString>
      <GameDBLocalizedString>
        <LocID>SYM_CRP_HYPERANDROGEN_DESCRIPTION</LocID>
        <Text>Kadında yüksek seviyede androjen bulunmasıdır.</Text>
      </GameDBLocalizedString>
      <GameDBLocalizedString>
        <LocID>SYM_CRP_SEBORRHEE</LocID>
        <Text>Sebore</Text>
      </GameDBLocalizedString>
      <GameDBLocalizedString>
        <LocID>SYM_CRP_SEBORRHEE_DESCRIPTION</LocID>
        <Text>Anormal derecede artmış sebum sekresyonu.</Text>
      </GameDBLocalizedString>
      <GameDBLocalizedString>
        <LocID>SYM_CRP_HIRSUTISME</LocID>
        <Text>Hirsutizm</Text>
      </GameDBLocalizedString>
      <GameDBLocalizedString>
        <LocID>SYM_CRP_HIRSUTISME_DESCRIPTION</LocID>
        <Text>Kadında normalde bulunmaması gereken veya az bulunması gereken yerlerde aşırı miktarda vücut kılı çıkmasıdır.</Text>
      </GameDBLocalizedString>
      <GameDBLocalizedString>
        <LocID>SYM_CRP_ACNE</LocID>
        <Text>Akne</Text>
      </GameDBLocalizedString>
      <GameDBLocalizedString>
        <LocID>SYM_CRP_ACNE_DESCRIPTION</LocID>
        <Text>Deride bulunan glandların ve saç foliküllerinin inflamasyonu sonucu ortaya çıkar. Adölesanlarda sıklıkla görülür, yüzde sivilcelerle karakterizedir.</Text>
      </GameDBLocalizedString>
      <GameDBLocalizedString>
        <LocID>SYM_CRP_ACANTHOSIS_NIGRICANS</LocID>
        <Text>Acanthosis nigricans</Text>
      </GameDBLocalizedString>
      <GameDBLocalizedString>
        <LocID>SYM_CRP_ACANTHOSIS_NIGRICANS_DESCRIPTION</LocID>
        <Text>Deride kadifemsi kalınlaşma ve koyulaşma ile karakterizedir, özellikle deri katlantılarında (koltuk altı, boyun, kasık gibi) görülür. Sıklıkla obezite, insülin direnci, hormonal düzensizlik veya ilaçlara bağlı gelişir, bununla beraber nadiren de olsa kanser (mide veya karaciğer gibi) bulgusu olabilir.</Text>
      </GameDBLocalizedString>
      <GameDBLocalizedString>
        <LocID>SYM_CRP_AMENORRHEE</LocID>
        <Text>Amenore</Text>
      </GameDBLocalizedString>
      <GameDBLocalizedString>
        <LocID>SYM_CRP_AMENORRHEE_DESCRIPTION</LocID>
        <Text>Adet kanamasının olmaması.</Text>
      </GameDBLocalizedString>
      <GameDBLocalizedString>
        <LocID>SYM_CRP_BOUFFEE_VASOMOTRICE</LocID>
        <Text>Flushing</Text>
      </GameDBLocalizedString>
      <GameDBLocalizedString>
        <LocID>SYM_CRP_BOUFFEE_VASOMOTRICE_DESCRIPTION</LocID>
        <Text>Çeşitli fizyolojik durumlara bağlı özellikle yüzde ve diğer deri kısımlarında kızarma şeklinde görülür.</Text>
      </GameDBLocalizedString>
      <GameDBLocalizedString>
        <LocID>SYM_CRP_SECHERESSE_VAGIN</LocID>
        <Text>Vajinal kuruluk</Text>
      </GameDBLocalizedString>
      <GameDBLocalizedString>
        <LocID>SYM_CRP_SECHERESSE_VAGIN_DESCRIPTION</LocID>
        <Text>Vajinal kuruluk azalmış östrojen seviyelerine bağlı ortaya çıkar.</Text>
      </GameDBLocalizedString>
      <GameDBLocalizedString>
        <LocID>SYM_CRP_DYSMENORRHEE</LocID>
        <Text>Dismenore</Text>
      </GameDBLocalizedString>
      <GameDBLocalizedString>
        <LocID>SYM_CRP_DYSMENORRHEE_DESCRIPTION</LocID>
        <Text>Ağrılı adet görme.</Text>
      </GameDBLocalizedString>
      <GameDBLocalizedString>
        <LocID>SYM_CRP_MENORRAGIE</LocID>
        <Text>Menoraji</Text>
      </GameDBLocalizedString>
      <GameDBLocalizedString>
        <LocID>SYM_CRP_MENORRAGIE_DESCRIPTION</LocID>
        <Text>Ağır adet kanaması.</Text>
      </GameDBLocalizedString>
      <GameDBLocalizedString>
        <LocID>SYM_CRP_LEUCORRHEE</LocID>
        <Text>Lökore</Text>
      </GameDBLocalizedString>
      <GameDBLocalizedString>
        <LocID>SYM_CRP_LEUCORRHEE_DESCRIPTION</LocID>
        <Text>Müköz membranda konjesyon veya inflamasyon sonucu ortaya çıkan vajinadan gelen beyazımsı yapışkan akıntı.</Text>
      </GameDBLocalizedString>
      <GameDBLocalizedString>
        <LocID>SYM_CRP_ULCERATION_GENITAL</LocID>
        <Text>Genital ülser</Text>
      </GameDBLocalizedString>
      <GameDBLocalizedString>
        <LocID>SYM_CRP_ULCERATION_GENITAL_DESCRIPTION</LocID>
        <Text>Tek veya multipl, ülseratif veya eroziv, inguinal lenfadenopatinin eşlik ettiği veya etmediği genital ülserler, cinsel yolla bulaşan enfeksiyonları akla getirmelidir.</Text>
      </GameDBLocalizedString>
      <GameDBLocalizedString>
        <LocID>SYM_CRP_CHANCRE_SYPHILIS</LocID>
        <Text>Sifilitik şankr</Text>
      </GameDBLocalizedString>
      <GameDBLocalizedString>
        <LocID>SYM_CRP_CHANCRE_SYPHILIS_DESCRIPTION</LocID>
        <Text>Sifilizin primer evre yarasıdır, ağrısız, sertleşmiş, erode olmuş bir papül görünümündedir. Enfeksiyon etkeninin giriş noktasında ortaya çıkar.</Text>
      </GameDBLocalizedString>
      <GameDBLocalizedString>
        <LocID>SYM_CRP_PREMATURE</LocID>
        <Text>Preterm</Text>
      </GameDBLocalizedString>
      <GameDBLocalizedString>
        <LocID>SYM_CRP_PREMATURE_DESCRIPTION</LocID>
        <Text>Miadından önce.</Text>
      </GameDBLocalizedString>
      <GameDBLocalizedString>
        <LocID>SYM_CRP_HPV_HR</LocID>
        <Text>Yüksek riskli HPV</Text>
      </GameDBLocalizedString>
      <GameDBLocalizedString>
        <LocID>SYM_CRP_HPV_HR_DESCRIPTION</LocID>
        <Text>Yüksek riskli HPV normal hücrelerin anormalleşmesine neden olabilir. Bu anormal hücreler zamanla kanserleşebilir. Genellikle serviksteki hücreleri etkiler; ancak vajina, vulva, anüs, penis, ağız ve boğazda da kansere neden olabilir.</Text>
      </GameDBLocalizedString>
      <GameDBLocalizedString>
        <LocID>SYM_CRP_DOULEUR_PELV</LocID>
        <Text>Pelvik ağrı</Text>
      </GameDBLocalizedString>
      <GameDBLocalizedString>
        <LocID>SYM_CRP_DOULEUR_PELV_DESCRIPTION</LocID>
        <Text>Pelvik bölgede ağrı.</Text>
      </GameDBLocalizedString>
      <GameDBLocalizedString>
        <LocID>SYM_CRP_COL_ROUGE</LocID>
        <Text>Servikal kızarıklık</Text>
      </GameDBLocalizedString>
      <GameDBLocalizedString>
        <LocID>SYM_CRP_COL_ROUGE_DESCRIPTION</LocID>
        <Text>Muayenede servikste kızarıklık görüldü.</Text>
      </GameDBLocalizedString>
      <GameDBLocalizedString>
        <LocID>SYM_CRP_VEGETATION_KYSTE</LocID>
        <Text>Ekstrakistik vejetasyon</Text>
      </GameDBLocalizedString>
      <GameDBLocalizedString>
        <LocID>SYM_CRP_VEGETATION_KYSTE_DESCRIPTION</LocID>
        <Text>USG'de vejetasyon tespit edildi.</Text>
      </GameDBLocalizedString>
      <GameDBLocalizedString>
        <LocID>SYM_CRP_TUMEFACTION</LocID>
        <Text>Meme ödemi</Text>
      </GameDBLocalizedString>
      <GameDBLocalizedString>
        <LocID>SYM_CRP_TUMEFACTION_DESCRIPTION</LocID>
        <Text>Memede anormal büyüme.</Text>
      </GameDBLocalizedString>
      <GameDBLocalizedString>
        <LocID>SYM_CRP_MASSE_HOMOGENE</LocID>
        <Text>Homojen kitle</Text>
      </GameDBLocalizedString>
      <GameDBLocalizedString>
        <LocID>SYM_CRP_MASSE_HOMOGENE_DESCRIPTION</LocID>
        <Text>USG'de homojen kitle tespit edildi.</Text>
      </GameDBLocalizedString>
      <GameDBLocalizedString>
        <LocID>SYM_CRP_CONTRACTION_UTERINE</LocID>
        <Text>Kontrakte pelvis</Text>
      </GameDBLocalizedString>
      <GameDBLocalizedString>
        <LocID>SYM_CRP_CONTRACTION_UTERINE_DESCRIPTION</LocID>
        <Text>Normal doğuma engel olacak şekilde pelvis çaplarının azaldığı pelvis türüdür.</Text>
      </GameDBLocalizedString>
      <GameDBLocalizedString>
        <LocID>SYM_CRP_ODEUR_VAGINALE</LocID>
        <Text>Vajinal koku</Text>
      </GameDBLocalizedString>
      <GameDBLocalizedString>
        <LocID>SYM_CRP_ODEUR_VAGINALE_DESCRIPTION</LocID>
        <Text>Güçlü "balık kokusuna benzer" vajinal koku.</Text>
      </GameDBLocalizedString>
      <GameDBLocalizedString>
        <LocID>SYM_CRP_POST_PARTUM</LocID>
        <Text>Postpartum</Text>
      </GameDBLocalizedString>
      <GameDBLocalizedString>
        <LocID>SYM_CRP_POST_PARTUM_DESCRIPTION</LocID>
        <Text>Doğumdan sonra.</Text>
      </GameDBLocalizedString>

	<!-- ### ### -->
	<!-- ######################################## Content From COMPLICATIONS ######################################## -->
	<!-- ### ### -->	
	
			<GameDBLocalizedString>	<LocID>SYM_CRP_PERITONITE</LocID>						<Text>Peritonit</Text>	</GameDBLocalizedString>
			<GameDBLocalizedString>	<LocID>SYM_CRP_ENDOCARDITIS</LocID>						<Text>Endokardit</Text>	</GameDBLocalizedString>
			<GameDBLocalizedString>	<LocID>SYM_CRP_DIABETES_SECONDARY</LocID>				<Text>Diyabet</Text>	</GameDBLocalizedString>
			<GameDBLocalizedString>	<LocID>SYM_CRP_CARPAL_TUNNEL</LocID>					<Text>Karpal Tünel</Text>	</GameDBLocalizedString>
			<GameDBLocalizedString>	<LocID>SYM_CRP_HEART_ATTACK</LocID>						<Text>Miyokardiyal enfarktüs</Text>	</GameDBLocalizedString>
			<GameDBLocalizedString>	<LocID>SYM_CRP_STK</LocID>								<Text>İnme</Text>	</GameDBLocalizedString>
			<GameDBLocalizedString>	<LocID>SYM_CRP_TAR</LocID>								<Text>Aort rüptürü</Text>	</GameDBLocalizedString>
			<GameDBLocalizedString>	<LocID>SYM_CRP_THROMBOSIS</LocID>						<Text>Tromboflebit</Text>	</GameDBLocalizedString>
		
	
	
	</LocalizedStrings>
  </GameDBStringTable>
</Database>